torchsnooper/__init__.py
TorchSnooper-0.8.dist-info/LICENSE
TorchSnooper-0.8.dist-info/METADATA
TorchSnooper-0.8.dist-info/WHEEL
TorchSnooper-0.8.dist-info/top_level.txt
TorchSnooper-0.8.dist-info/RECORD
