Metadata-Version: 2.1
Name: TorchSnooper
Version: 0.8
Summary: Debug PyTorch code using PySnooper.
Home-page: https://github.com/zasdfgbnm/TorchSnooper
Author: Xiang Gao
Author-email: qasdfgtyuiop@gmail.com
License: UNKNOWN
Platform: UNKNOWN
Requires-Dist: pysnooper (>=0.1.0)
Requires-Dist: numpy
